[
  {
    "op": "54",
    "offset": 0,
    "args": [
      "u8:9",
      "black"
    ]
  },
  {
    "op": "6B",
    "offset": 8,
    "args": [
      "u8:20"
    ]
  },
  {
    "op": "54",
    "offset": 10,
    "args": [
      "u8:9",
      "black"
    ]
  },
  {
    "op": "20",
    "offset": 18,
    "args": [
      "u8:3"
    ]
  },
  {
    "op": "54",
    "offset": 20,
    "args": [
      "u8:8",
      "bg05"
    ]
  },
  {
    "op": "15",
    "offset": 27,
    "args": [
      "\u0001\u0002……今日も大学か。\u0005\u0001いつものように用意をし、\u0005"
    ]
  },
  {
    "op": "54",
    "offset": 76,
    "args": [
      "u8:9",
      "white"
    ]
  },
  {
    "op": "54",
    "offset": 84,
    "args": [
      "u8:8",
      "bg06"
    ]
  },
  {
    "op": "15",
    "offset": 91,
    "args": [
      "\u0001\u0002「行って来るよ」\u0005\u0001ルミに見送られてドアをくぐる。\u0005誰かに見送ってもらうのはここ数年無かったけど、やっぱり良いものだと実感した。\u0005"
    ]
  },
  {
    "op": "15",
    "offset": 221,
    "args": [
      "\u0001\u0002なんとなく安心できるって言うんだろうか……、\u0005とにかく嬉しい。\u0005"
    ]
  },
  {
    "op": "54",
    "offset": 287,
    "args": [
      "u8:3",
      "bg00"
    ]
  },
  {
    "op": "15",
    "offset": 294,
    "args": [
      "\u0001\u0002いつもの通りを抜け……。\u0005"
    ]
  },
  {
    "op": "54",
    "offset": 323,
    "args": [
      "u8:3",
      "bg11"
    ]
  },
  {
    "op": "15",
    "offset": 330,
    "args": [
      "\u0001\u0002大学に着いた。\u0005"
    ]
  },
  {
    "op": "15",
    "offset": 349,
    "args": [
      "\u0001\u0002着いたところで相変わらずの日常が待っているだけなんだけど………。\u0005"
    ]
  },
  {
    "op": "54",
    "offset": 418,
    "args": [
      "u8:9",
      "white"
    ]
  },
  {
    "op": "6B",
    "offset": 426,
    "args": [
      "u8:15"
    ]
  },
  {
    "op": "21",
    "offset": 428,
    "args": []
  },
  {
    "op": "54",
    "offset": 429,
    "args": [
      "u8:8",
      "bg09"
    ]
  },
  {
    "op": "15",
    "offset": 436,
    "args": [
      "\u0001\u0002更にいつも通りの講義が終わったところで、裕也が話しかけてきた。\u0005"
    ]
  },
  {
    "op": "20",
    "offset": 503,
    "args": [
      "u8:6"
    ]
  },
  {
    "op": "55",
    "offset": 505,
    "args": [
      "u8:8",
      "cgyu0000"
    ]
  },
  {
    "op": "15",
    "offset": 516,
    "args": [
      "\u0001\u0002裕也「よ、チアキ。\u0005お勤めごくろーさん！」\u0005"
    ]
  },
  {
    "op": "15",
    "offset": 562,
    "args": [
      "\u0001\u0002智秋「…相変わらずだな」\u0005"
    ]
  },
  {
    "op": "15",
    "offset": 591,
    "args": [
      "\u0001\u0002裕也「智秋もな」\u0005"
    ]
  },
  {
    "op": "15",
    "offset": 612,
    "args": [
      "\u0001\u0002智秋「……で？\u0005何か用か？」\u0005"
    ]
  },
  {
    "op": "15",
    "offset": 644,
    "args": [
      "\u0001\u0002裕也「今日サ、チョット買い物に付き合ってくンない？」\u0005"
    ]
  },
  {
    "op": "15",
    "offset": 701,
    "args": [
      "\u0001\u0002智秋「買い物？\u0005…何買うんだ？」\u0005"
    ]
  },
  {
    "op": "15",
    "offset": 737,
    "args": [
      "\u0001\u0002裕也「いや、別にこれといってないンだけどナ」\u0005"
    ]
  },
  {
    "op": "15",
    "offset": 786,
    "args": [
      "\u0001\u0002智秋「なんだよ、それ」\u0005"
    ]
  },
  {
    "op": "15",
    "offset": 813,
    "args": [
      "\u0001\u0002裕也「まー、そう言うなって。最近付き合い悪いゼ？」\u0005"
    ]
  },
  {
    "op": "15",
    "offset": 868,
    "args": [
      "\u0001\u0002智秋「…どうすっかな」\u0005"
    ]
  },
  {
    "op": "55",
    "offset": 895,
    "args": [
      "u8:8",
      "cgyu0100"
    ]
  },
  {
    "op": "15",
    "offset": 906,
    "args": [
      "\u0001\u0002裕也「そーだ！ルミちゃんも誘えよ」\u0005"
    ]
  },
  {
    "op": "15",
    "offset": 945,
    "args": [
      "\u0001\u0002智秋「ルミを！？」\u0005"
    ]
  },
  {
    "op": "15",
    "offset": 968,
    "args": [
      "\u0001\u0002裕也「なにドーヨーしてるんだよ」\u0005\u0001裕也がいつものにやにや笑いを浮かべる。\u0005最近なんかつけ込まれることが多いな…。\u0005そのうちにこの借りは返さないと。\u0005"
    ]
  },
  {
    "op": "15",
    "offset": 1117,
    "args": [
      "\u0001\u0002智秋「別になんでもねーよ」\u0005"
    ]
  },
  {
    "op": "55",
    "offset": 1148,
    "args": [
      "u8:8",
      "cgyu0000"
    ]
  },
  {
    "op": "15",
    "offset": 1159,
    "args": [
      "\u0001\u0002裕也「へ～、左様ですか」\u0005\u0001案の定からんできた。\u0005"
    ]
  },
  {
    "op": "15",
    "offset": 1210,
    "args": [
      "\u0001\u0002智秋「そうだよ！」\u0005"
    ]
  },
  {
    "op": "15",
    "offset": 1233,
    "args": [
      "\u0001\u0002裕也「ま、いっか。で、どーする？」\u0005"
    ]
  },
  {
    "op": "15",
    "offset": 1272,
    "args": [
      "\u0001\u0002智秋「そうだな…」\u0005\u0001どうしようか……昨日の一件もあるしな。\u0005買い物に行くって言えば、間違いなくついて来たがるだろうし……。\u0005"
    ]
  },
  {
    "op": "15",
    "offset": 1398,
    "args": [
      "\u0001\u0002嘘を言って出かけるっていうことも出来るのだが、ルミを騙すのは気が引ける。\u0005\u0001…それに俺、嘘付くの上手くないしなぁ。\u0005"
    ]
  },
  {
    "op": "15",
    "offset": 1515,
    "args": [
      "\u0001\u0002裕也「そんなに考え込むようなコトかよ？」\u0005"
    ]
  },
  {
    "op": "15",
    "offset": 1560,
    "args": [
      "\u0001\u0002智秋「うるせー、いろいろあるんだよ」\u0005"
    ]
  },
  {
    "op": "15",
    "offset": 1601,
    "args": [
      "\u0001\u0002裕也「あ、そーか！」\u0005"
    ]
  },
  {
    "op": "15",
    "offset": 1626,
    "args": [
      "\u0001ルミちゃんを独り占め…"
    ]
  },
  {
    "op": "5B",
    "offset": 1651,
    "args": [
      "u8:0",
      "se02i.wav"
    ]
  },
  {
    "op": "15",
    "offset": 1663,
    "args": [
      "\u0001ごふぅ？」"
    ]
  },
  {
    "op": "6B",
    "offset": 1676,
    "args": [
      "u8:3"
    ]
  },
  {
    "op": "4C 00",
    "offset": 1678,
    "args": []
  },
  {
    "op": "50 07",
    "offset": 1680,
    "args": []
  },
  {
    "op": "15",
    "offset": 1682,
    "args": [
      "\u0001\u0002奴が言い終える前に、俺の拳がその顔面へヒットした。\u0005"
    ]
  },
  {
    "op": "15",
    "offset": 1737,
    "args": [
      "\u0001\u0002智秋「くだらない詮索はよせ。\u0005……いちいちつまらんものを殴らなきゃならん」\u0005"
    ]
  },
  {
    "op": "55",
    "offset": 1815,
    "args": [
      "u8:7",
      "cgyu0300"
    ]
  },
  {
    "op": "15",
    "offset": 1826,
    "args": [
      "\u0001\u0002裕也「…ってーな！！殴るこたねーだろ？\u0005それに『つまらんもの』ってナンだよ！」\u0005"
    ]
  },
  {
    "op": "15",
    "offset": 1908,
    "args": [
      "\u0001\u0002智秋「おまえ以外に誰がいるんだよ」\u0005"
    ]
  },
  {
    "op": "15",
    "offset": 1947,
    "args": [
      "\u0001\u0002裕也「むっきー！」\u0005"
    ]
  },
  {
    "op": "15",
    "offset": 1970,
    "args": [
      "\u0001\u0002智秋「…猿のマネか？」\u0005"
    ]
  },
  {
    "op": "15",
    "offset": 1997,
    "args": [
      "\u0001\u0002裕也「誰が好き好んでっ…」\u0005"
    ]
  },
  {
    "op": "55",
    "offset": 2028,
    "args": [
      "u8:8",
      "cgyu0200"
    ]
  },
  {
    "op": "15",
    "offset": 2039,
    "args": [
      "\u0001\u0002裕也「……はぁ。\u0005……やめようや、このノリ」\u0005\u0001いかにもぐったりといった感じで肩を落とした。\u0005"
    ]
  },
  {
    "op": "15",
    "offset": 2133,
    "args": [
      "\u0001\u0002智秋「なんで？」\u0005"
    ]
  },
  {
    "op": "15",
    "offset": 2154,
    "args": [
      "\u0001\u0002裕也「…なんか俺ばっかり損な役回りじゃネーか」\u0005"
    ]
  },
  {
    "op": "15",
    "offset": 2205,
    "args": [
      "\u0001\u0002智秋「気のせいだろ？」\u0005"
    ]
  },
  {
    "op": "15",
    "offset": 2232,
    "args": [
      "\u0001\u0002裕也「気のせいじゃネーよ！\u0005……で、どーすンだよ？」\u0005"
    ]
  },
  {
    "op": "15",
    "offset": 2288,
    "args": [
      "\u0001\u0002智秋「は？\u0005…何が？」\u0005"
    ]
  },
  {
    "op": "15",
    "offset": 2314,
    "args": [
      "\u0001\u0002裕也「『…何が？』じゃネーって！！買い物だよ、か・い・も・のっ！！」\u0005\u0001はぁはぁと肩で息を付いている。\u0005そろそろ半ギレになってきたな、この位にしとこう。\u0005"
    ]
  },
  {
    "op": "15",
    "offset": 2468,
    "args": [
      "\u0001\u0002智秋「分かった、付き合うよ」\u0005"
    ]
  },
  {
    "op": "15",
    "offset": 2501,
    "args": [
      "\u0001\u0002裕也「ルミちゃんは？」\u0005"
    ]
  },
  {
    "op": "15",
    "offset": 2528,
    "args": [
      "\u0001\u0002智秋「うーん…\u0005…\u0005…\u0005ま、いいだろ」\u0005\u0001二人だと〝いかにも〟だけど、三人なら人に見られても平気だろう。\u0005ルミもそろそろ外界との接触を持った方が良いだろうし。\u0005"
    ]
  },
  {
    "op": "15",
    "offset": 2685,
    "args": [
      "\u0001\u0002裕也「オッケ。じゃあ今からチアキのトコ行こうか」\u0005"
    ]
  },
  {
    "op": "15",
    "offset": 2738,
    "args": [
      "\u0001\u0002智秋「…何でそうなるんだよ？」\u0005"
    ]
  },
  {
    "op": "55",
    "offset": 2773,
    "args": [
      "u8:8",
      "cgyu0100"
    ]
  },
  {
    "op": "15",
    "offset": 2784,
    "args": [
      "\u0001\u0002裕也「いいじゃネーか。気にすンなって！」\u0005\u0001バシ、バシッ、と俺の肩を叩く。\u0005"
    ]
  },
  {
    "op": "4C 00",
    "offset": 2861,
    "args": []
  },
  {
    "op": "50 07",
    "offset": 2863,
    "args": []
  },
  {
    "op": "15",
    "offset": 2865,
    "args": [
      "\u0001\u0002智秋「おい？待てよ！」\u0005\u0001先に歩き出した裕也に慌てて声をかけるが、\u0005…予想通り俺の言葉は聞き流された。\u0005"
    ]
  },
  {
    "op": "15",
    "offset": 2969,
    "args": [
      "\u0001\u0002裕也「早く来いよ」\u0005"
    ]
  },
  {
    "op": "15",
    "offset": 2992,
    "args": [
      "\u0001\u0002智秋「おい、待てって！？」\u0005"
    ]
  },
  {
    "op": "54",
    "offset": 3023,
    "args": [
      "u8:9",
      "black"
    ]
  },
  {
    "op": "15",
    "offset": 3031,
    "args": [
      "\u0001\u0002…。\u0005"
    ]
  },
  {
    "op": "15",
    "offset": 3040,
    "args": [
      "\u0001\u0002……。\u0005"
    ]
  },
  {
    "op": "15",
    "offset": 3051,
    "args": [
      "\u0001\u0002………。\u0005"
    ]
  },
  {
    "op": "54",
    "offset": 3064,
    "args": [
      "u8:8",
      "bg05"
    ]
  },
  {
    "op": "15",
    "offset": 3071,
    "args": [
      "\u0001\u0002…結局裕也の押しの強さに負けて、俺の部屋に上がり込まれてしまった。\u0005"
    ]
  },
  {
    "op": "55",
    "offset": 3142,
    "args": [
      "u8:8",
      "cgyu0010"
    ]
  },
  {
    "op": "15",
    "offset": 3153,
    "args": [
      "\u0001\u0002裕也「なンだよ、まるでオレが無理矢理上がり込んだみてーじゃネーか」\u0005"
    ]
  },
  {
    "op": "15",
    "offset": 3224,
    "args": [
      "\u0001\u0002智秋「……無理矢理だろ」\u0005"
    ]
  },
  {
    "op": "55",
    "offset": 3253,
    "args": [
      "u8:8",
      "cgru0010"
    ]
  },
  {
    "op": "15",
    "offset": 3264,
    "args": [
      "\u0001\u0002ルミ「ふふふ」\u0005\u0001そんな二人のやりとりをルミが可笑しそうな顔で見ている。\u0005"
    ]
  },
  {
    "op": "15",
    "offset": 3339,
    "args": [
      "\u0001\u0002ルミ「ホントに仲が良いんだね、おにいちゃん達」\u0005"
    ]
  },
  {
    "op": "15",
    "offset": 3390,
    "args": [
      "\u0001\u0002智秋「こんな奴と一括りにしないでくれ」\u0005"
    ]
  },
  {
    "op": "55",
    "offset": 3433,
    "args": [
      "u8:8",
      "cgyu0010"
    ]
  },
  {
    "op": "15",
    "offset": 3444,
    "args": [
      "\u0001\u0002裕也「ダロ？シンユーなンだ」\u0005"
    ]
  },
  {
    "op": "55",
    "offset": 3477,
    "args": [
      "u8:8",
      "cgru0010"
    ]
  },
  {
    "op": "15",
    "offset": 3488,
    "args": [
      "\u0001\u0002ルミ「うん、私もそう思うよ」\u0005\u0001…俺の抗議をよそに話が進んでいく。\u0005"
    ]
  },
  {
    "op": "55",
    "offset": 3557,
    "args": [
      "u8:8",
      "cgyu0010"
    ]
  },
  {
    "op": "15",
    "offset": 3568,
    "args": [
      "\u0001\u0002裕也「チアキ～」\u0005\u0001裕也の声が急に猫撫で声になった。\u0005"
    ]
  },
  {
    "op": "15",
    "offset": 3623,
    "args": [
      "\u0001\u0002智秋「んだよ？気持ち悪い声出すんじゃねーって」\u0005"
    ]
  },
  {
    "op": "15",
    "offset": 3674,
    "args": [
      "\u0001\u0002裕也「お腹空いたぁ～」\u0005"
    ]
  },
  {
    "op": "55",
    "offset": 3701,
    "args": [
      "u8:8",
      "cgru0110"
    ]
  },
  {
    "op": "15",
    "offset": 3712,
    "args": [
      "\u0001\u0002ルミ「私もお腹空いたな」\u0005"
    ]
  },
  {
    "op": "15",
    "offset": 3741,
    "args": [
      "\u0001\u0002智秋「…裕也くん」\u0005"
    ]
  },
  {
    "op": "55",
    "offset": 3764,
    "args": [
      "u8:8",
      "cgyu0010"
    ]
  },
  {
    "op": "15",
    "offset": 3775,
    "args": [
      "\u0001\u0002裕也「ン？」\u0005"
    ]
  },
  {
    "op": "15",
    "offset": 3792,
    "args": [
      "\u0001\u0002智秋「…初めからそれが狙いだったのかい？」\u0005"
    ]
  },
  {
    "op": "55",
    "offset": 3839,
    "args": [
      "u8:8",
      "cgyu0110"
    ]
  },
  {
    "op": "15",
    "offset": 3850,
    "args": [
      "\u0001\u0002裕也「ハハハ、まさか」\u0005\u0001白々しい声を立てて笑う。\u0005"
    ]
  },
  {
    "op": "15",
    "offset": 3903,
    "args": [
      "\u0001\u0002智秋「怒らないからいってみ？」\u0005\u0001穏やかに問いつめる。\u0005"
    ]
  },
  {
    "op": "15",
    "offset": 3960,
    "args": [
      "\u0001\u0002裕也「まあな…」\u0005"
    ]
  },
  {
    "op": "5B",
    "offset": 3981,
    "args": [
      "u8:0",
      "se02h.wav"
    ]
  },
  {
    "op": "4C 00",
    "offset": 3993,
    "args": []
  },
  {
    "op": "50 07",
    "offset": 3995,
    "args": []
  },
  {
    "op": "15",
    "offset": 3997,
    "args": [
      "\u0001\u0002「ぐはぁっ！？」\u0005"
    ]
  },
  {
    "op": "15",
    "offset": 4018,
    "args": [
      "\u0001\u0002すぱーんと俺の右フックが綺麗に入った。\u0005"
    ]
  },
  {
    "op": "15",
    "offset": 4061,
    "args": [
      "\u0001\u0002智秋「……さて、飯でも作るか」\u0005\u0001さっさと料理の準備に取りかかる。\u0005"
    ]
  },
  {
    "op": "15",
    "offset": 4130,
    "args": [
      "\u0001\u0002裕也「思いっきり怒ってるじゃネーか！」\u0005"
    ]
  },
  {
    "op": "15",
    "offset": 4173,
    "args": [
      "\u0001\u0002ルミ「…大丈夫、裕也ちゃん？」\u0005\u0001地面でへばっている裕也に、心配そうな顔でルミが問いかけた。\u0005"
    ]
  },
  {
    "op": "15",
    "offset": 4268,
    "args": [
      "\u0001\u0002智秋「ルミ、気にしなくてもいいよ。\u0005親愛の表現だから」\u0005\u0001俺の言葉にルミが神妙な顔で呟く。\u0005"
    ]
  },
  {
    "op": "55",
    "offset": 4360,
    "args": [
      "u8:8",
      "cgru0310"
    ]
  },
  {
    "op": "15",
    "offset": 4371,
    "args": [
      "\u0001\u0002ルミ「親友って……\u0005大変なんだね」\u0005\u0001あの～\u0005……そこで納得されても困るんだけど…。\u0005"
    ]
  },
  {
    "op": "54",
    "offset": 4456,
    "args": [
      "u8:8",
      "black"
    ]
  },
  {
    "op": "21",
    "offset": 4464,
    "args": []
  },
  {
    "op": "15",
    "offset": 4465,
    "args": [
      "\u0001\u0002…。\u0005"
    ]
  },
  {
    "op": "15",
    "offset": 4474,
    "args": [
      "\u0001\u0002……。\u0005"
    ]
  },
  {
    "op": "15",
    "offset": 4485,
    "args": [
      "\u0001\u0002………。\u0005"
    ]
  },
  {
    "op": "20",
    "offset": 4498,
    "args": [
      "u8:5"
    ]
  },
  {
    "op": "54",
    "offset": 4500,
    "args": [
      "u8:8",
      "bg05"
    ]
  },
  {
    "op": "55",
    "offset": 4507,
    "args": [
      "u8:8",
      "cgyu0010"
    ]
  },
  {
    "op": "15",
    "offset": 4518,
    "args": [
      "\u0001\u0002智秋「さて、そろそろ行こうか？」\u0005\u0001昼食を食べ終え、リビングでくつろいでいる二人に声をかける。\u0005"
    ]
  },
  {
    "op": "55",
    "offset": 4615,
    "args": [
      "u8:8",
      "cgru0310"
    ]
  },
  {
    "op": "15",
    "offset": 4626,
    "args": [
      "\u0001\u0002ルミ「えっ？どこか出かけるの？」\u0005"
    ]
  },
  {
    "op": "15",
    "offset": 4663,
    "args": [
      "\u0001\u0002智秋「あ、そういえば、まだ言ってなかったか…」\u0005\u0001言いながら裕也に視線を向ける。\u0005"
    ]
  },
  {
    "op": "15",
    "offset": 4746,
    "args": [
      "\u0001\u0002裕也「あのサ、買い物行こうと思うンだけど、\u0005ルミちゃんも一緒にどう？」\u0005"
    ]
  },
  {
    "op": "55",
    "offset": 4820,
    "args": [
      "u8:8",
      "cgru0010"
    ]
  },
  {
    "op": "15",
    "offset": 4831,
    "args": [
      "\u0001\u0002ルミ「えっ？私も行っていいの？」\u0005\u0001ルミが俺の方を向く。\u0005…おそらく俺の許可を待っているんだろう。\u0005"
    ]
  },
  {
    "op": "15",
    "offset": 4931,
    "args": [
      "\u0001\u0002智秋「ああ。\u0005…でもあんまり期待しない方がいいな。大したものじゃ…」\u0005"
    ]
  },
  {
    "op": "55",
    "offset": 5003,
    "args": [
      "u8:0",
      "cgru0110"
    ]
  },
  {
    "op": "15",
    "offset": 5014,
    "args": [
      "\u0001\u0002ルミ「やったー！」\u0005\u0001がばっ。\u0005俺の言葉を遮ってルミが久々に抱きついてきた。\u0005もはやお約束といった感じで俺の躰が傾いていく。\u0005"
    ]
  },
  {
    "op": "21",
    "offset": 5139,
    "args": []
  },
  {
    "op": "15",
    "offset": 5140,
    "args": [
      "\u0001\u0002…そして後に続くのは……\u0001"
    ]
  },
  {
    "op": "6B",
    "offset": 5169,
    "args": [
      "u8:5"
    ]
  },
  {
    "op": "15",
    "offset": 5171,
    "args": [
      "\u0001\u0002…"
    ]
  },
  {
    "op": "6B",
    "offset": 5177,
    "args": [
      "u8:5"
    ]
  },
  {
    "op": "15",
    "offset": 5179,
    "args": [
      "\u0001…"
    ]
  },
  {
    "op": "6B",
    "offset": 5184,
    "args": [
      "u8:5"
    ]
  },
  {
    "op": "5B",
    "offset": 5186,
    "args": [
      "u8:0",
      "se02g.wav"
    ]
  },
  {
    "op": "15",
    "offset": 5198,
    "args": [
      "\u0001\u0002………ごんっ！\u0005"
    ]
  },
  {
    "op": "15",
    "offset": 5217,
    "args": [
      "\u0001\u0002俺が頭を打つ音だった。\u0005"
    ]
  },
  {
    "op": "54",
    "offset": 5244,
    "args": [
      "u8:9",
      "white"
    ]
  },
  {
    "op": "15",
    "offset": 5252,
    "args": [
      "\u0001\u0002…。\u0005"
    ]
  },
  {
    "op": "15",
    "offset": 5261,
    "args": [
      "\u0001\u0002……。\u0005"
    ]
  },
  {
    "op": "15",
    "offset": 5272,
    "args": [
      "\u0001\u0002………。\u0005"
    ]
  },
  {
    "op": "15",
    "offset": 5285,
    "args": [
      "\u0001\u0002「……い」\u0005"
    ]
  },
  {
    "op": "54",
    "offset": 5300,
    "args": [
      "u8:9",
      "bg05"
    ]
  },
  {
    "op": "55",
    "offset": 5307,
    "args": [
      "u8:8",
      "cgyu0110"
    ]
  },
  {
    "op": "15",
    "offset": 5318,
    "args": [
      "\u0001\u0002「おーい、生きてるかぁ？」\u0005"
    ]
  },
  {
    "op": "55",
    "offset": 5349,
    "args": [
      "u8:8",
      "cgru0310"
    ]
  },
  {
    "op": "15",
    "offset": 5360,
    "args": [
      "\u0001\u0002ルミ「…おにいちゃん？大丈夫！？」\u0005\u0001慌てて俺の上から退いたルミが、心配そうに声をかけてきた。\u0005"
    ]
  },
  {
    "op": "15",
    "offset": 5457,
    "args": [
      "\u0001\u0002智秋「…だ、だいじょうぶ」\u0005\u0001何とか返事をしたものの、全く大丈夫じゃなかった。\u0005"
    ]
  },
  {
    "op": "15",
    "offset": 5538,
    "args": [
      "\u0001\u0002ルミ「…どうしよう？…おにいちゃん！？」\u0005\u0001ルミがおろおろして俺の上体を激しく揺する。\u0005"
    ]
  },
  {
    "op": "15",
    "offset": 5627,
    "args": [
      "\u0001\u0002ううっ…"
    ]
  },
  {
    "op": "6B",
    "offset": 5639,
    "args": [
      "u8:12"
    ]
  },
  {
    "op": "15",
    "offset": 5641,
    "args": [
      "\u0001世界が"
    ]
  },
  {
    "op": "6B",
    "offset": 5650,
    "args": [
      "u8:8"
    ]
  },
  {
    "op": "15",
    "offset": 5652,
    "args": [
      "\u0001…"
    ]
  },
  {
    "op": "6B",
    "offset": 5657,
    "args": [
      "u8:4"
    ]
  },
  {
    "op": "15",
    "offset": 5659,
    "args": [
      "\u0001…"
    ]
  },
  {
    "op": "6B",
    "offset": 5664,
    "args": [
      "u8:8"
    ]
  },
  {
    "op": "15",
    "offset": 5666,
    "args": [
      "\u0001回"
    ]
  },
  {
    "op": "6B",
    "offset": 5671,
    "args": [
      "u8:4"
    ]
  },
  {
    "op": "15",
    "offset": 5673,
    "args": [
      "\u0001…"
    ]
  },
  {
    "op": "6B",
    "offset": 5678,
    "args": [
      "u8:4"
    ]
  },
  {
    "op": "15",
    "offset": 5680,
    "args": [
      "\u0001…る。"
    ]
  },
  {
    "op": "6B",
    "offset": 5689,
    "args": [
      "u8:10"
    ]
  },
  {
    "op": "4C 00",
    "offset": 5691,
    "args": []
  },
  {
    "op": "50 07",
    "offset": 5693,
    "args": []
  },
  {
    "op": "15",
    "offset": 5695,
    "args": [
      "\u0001\u0002そんな二人の様子を見て裕也がゲラゲラと笑い転げている。\u0005\u0001ちくしょう\u0005……後で覚えてろよ。\u0005"
    ]
  },
  {
    "op": "54",
    "offset": 5787,
    "args": [
      "u8:10",
      "black"
    ]
  },
  {
    "op": "15",
    "offset": 5795,
    "args": [
      "\u0001\u0002裕也に復讐を誓いながら俺の意識はブラックアウトしていった。\u0005"
    ]
  },
  {
    "op": "15",
    "offset": 5858,
    "args": [
      "\u0001\u0002………。\u0005"
    ]
  },
  {
    "op": "15",
    "offset": 5871,
    "args": [
      "\u0001\u0002……。\u0005"
    ]
  },
  {
    "op": "15",
    "offset": 5882,
    "args": [
      "\u0001\u0002…。\u0005"
    ]
  },
  {
    "op": "20",
    "offset": 5891,
    "args": [
      "u8:5"
    ]
  },
  {
    "op": "54",
    "offset": 5893,
    "args": [
      "u8:8",
      "bg03"
    ]
  },
  {
    "op": "15",
    "offset": 5900,
    "args": [
      "\u0001\u0002結局その後、\u0005俺が目を覚ましてから三人で買い物に出かけた。\u0005今は近くにある商店街の洋服屋に来ているのだが、はっきり言ってろくなモノではなかった。\u0005"
    ]
  },
  {
    "op": "15",
    "offset": 6047,
    "args": [
      "\u0001\u0002特に欲しい物もなかったので、必然的に裕也とルミが品定めしているのを眺める事になってしまう。\u0005"
    ]
  },
  {
    "op": "15",
    "offset": 6142,
    "args": [
      "\u0001\u0002「………どう思う？」\u0005"
    ]
  },
  {
    "op": "15",
    "offset": 6167,
    "args": [
      "\u0001\u0002「…なぁ、智秋ってば！」\u0005"
    ]
  },
  {
    "op": "15",
    "offset": 6196,
    "args": [
      "\u0001\u0002智秋「……ん？\u0005…何だ？」\u0005\u0001裕也の声で我に帰る。\u0005"
    ]
  },
  {
    "op": "55",
    "offset": 6248,
    "args": [
      "u8:8",
      "cgyu0110"
    ]
  },
  {
    "op": "15",
    "offset": 6259,
    "args": [
      "\u0001\u0002裕也「…やっぱり聞いてなかったか。\u0005これどう思う？」\u0005\u0001裕也が〝しょうがないなぁ〟といった感じで問いかけてくる。\u0005見れば、両手に二着の服を持っていた。\u0005"
    ]
  },
  {
    "op": "15",
    "offset": 6410,
    "args": [
      "\u0001\u0002片方が…赤と黒の斑模様のシャツで、もう一方は…\u0005駄目だ、俺には言えねぇ……。\u0005"
    ]
  },
  {
    "op": "15",
    "offset": 6490,
    "args": [
      "\u0001\u0002智秋「…いっかい死んで来い」\u0005\u0001俺は正直な感想を述べた。\u0005"
    ]
  },
  {
    "op": "15",
    "offset": 6549,
    "args": [
      "\u0001\u0002裕也「なんだよ、イケてるじゃネーか」\u0005"
    ]
  },
  {
    "op": "15",
    "offset": 6590,
    "args": [
      "\u0001\u0002智秋「………冗談だろ？」\u0005"
    ]
  },
  {
    "op": "15",
    "offset": 6619,
    "args": [
      "\u0001\u0002裕也「冗談だ」\u0005"
    ]
  },
  {
    "op": "15",
    "offset": 6638,
    "args": [
      "\u0001\u0002智秋「………」\u0005"
    ]
  },
  {
    "op": "15",
    "offset": 6657,
    "args": [
      "\u0001\u0002裕也「………」\u0005"
    ]
  },
  {
    "op": "15",
    "offset": 6676,
    "args": [
      "\u0001\u0002智秋「………」\u0005"
    ]
  },
  {
    "op": "15",
    "offset": 6695,
    "args": [
      "\u0001\u0002ツッ込みを入れようとしたその時、\u0005\u0001「あ、それ、可愛いね！」\u0005\u0001横から、ルミの弾むような声が聞こえた。\u0005"
    ]
  },
  {
    "op": "15",
    "offset": 6798,
    "args": [
      "\u0001\u0002ルミが指し示した先には、\u0005…俺がさっき正視出来なかったシャツがあった。\u0005"
    ]
  },
  {
    "op": "15",
    "offset": 6872,
    "args": [
      "\u0001\u0002智秋「………」\u0001裕也「………」\u0005\u0001俺と裕也が仲良く凍り付く。\u0005それから二呼吸程置いて、首をぎこちなくルミの方に回した。\u0005"
    ]
  },
  {
    "op": "55",
    "offset": 6991,
    "args": [
      "u8:8",
      "cgru0010"
    ]
  },
  {
    "op": "15",
    "offset": 7002,
    "args": [
      "\u0001\u0002ルミ「…どうしたの？」\u0005\u0001ルミが不思議そうな顔で俺と裕也を見比べる。\u0005"
    ]
  },
  {
    "op": "15",
    "offset": 7073,
    "args": [
      "\u0001\u0002智秋「ルミ」\u0005"
    ]
  },
  {
    "op": "15",
    "offset": 7090,
    "args": [
      "\u0001\u0002ルミ「なあに？」\u0005"
    ]
  },
  {
    "op": "15",
    "offset": 7111,
    "args": [
      "\u0001\u0002智秋「…これ、本当に可愛いと思うか？」\u0005"
    ]
  },
  {
    "op": "15",
    "offset": 7154,
    "args": [
      "\u0001\u0002ルミ「え、可愛いよ。そう思わない？」\u0005"
    ]
  },
  {
    "op": "15",
    "offset": 7195,
    "args": [
      "\u0001\u0002智秋「………」\u0005\u0001…ルミにそこまで断言されると自信が無くなってきた。\u0005もう一度裕也の持っているシャツを見てみる。\u0005"
    ]
  },
  {
    "op": "4C 00",
    "offset": 7309,
    "args": []
  },
  {
    "op": "50 07",
    "offset": 7311,
    "args": []
  },
  {
    "op": "15",
    "offset": 7313,
    "args": [
      "\u0001\u0002それはくすんだ緑の地にプリントが施された物だった。\u0005地の色も確かに個性的だが、プリントされた絵に比べれば些末なことだ。\u0005"
    ]
  },
  {
    "op": "15",
    "offset": 7435,
    "args": [
      "\u0001\u0002…例えるなら、ラッ○ンの絵をピカ○風にアレンジし損ねた感じだろうか。\u0005"
    ]
  },
  {
    "op": "15",
    "offset": 7508,
    "args": [
      "\u0001\u0002イルカだかカエルだか分からない、見るからにグロテスクな代物が油の中を漂っている。\u0005…なんというか、独創性という言葉で片づけるのも気が引ける絵だった。\u0005"
    ]
  },
  {
    "op": "55",
    "offset": 7660,
    "args": [
      "u8:8",
      "cgru0010"
    ]
  },
  {
    "op": "15",
    "offset": 7671,
    "args": [
      "\u0001\u0002ルミ「…いいなあ」\u0005\u0001シャツを見つめながら、うっとりとした声でルミが呟く。\u0005"
    ]
  },
  {
    "op": "55",
    "offset": 7748,
    "args": [
      "u8:8",
      "cgyu0010"
    ]
  },
  {
    "op": "15",
    "offset": 7759,
    "args": [
      "\u0001\u0002裕也「…ルミちゃん」\u0005\u0001そんなルミに、裕也が話しかけた。\u0005"
    ]
  },
  {
    "op": "55",
    "offset": 7818,
    "args": [
      "u8:8",
      "cgru0010"
    ]
  },
  {
    "op": "15",
    "offset": 7829,
    "args": [
      "\u0001\u0002ルミ「なに？」\u0005"
    ]
  },
  {
    "op": "55",
    "offset": 7848,
    "args": [
      "u8:8",
      "cgyu0010"
    ]
  },
  {
    "op": "15",
    "offset": 7859,
    "args": [
      "\u0001\u0002裕也「…これ、ルミちゃんに譲ろうか？」\u0005"
    ]
  },
  {
    "op": "55",
    "offset": 7902,
    "args": [
      "u8:8",
      "cgru0110"
    ]
  },
  {
    "op": "15",
    "offset": 7913,
    "args": [
      "\u0001\u0002ルミ「ほんとっ！？」\u0005\u0001ルミが心底嬉しそうな顔をして裕也をみつめた。\u0005"
    ]
  },
  {
    "op": "15",
    "offset": 7984,
    "args": [
      "\u0001\u0002智秋「ルミ」\u0005\u0001俺は少し真面目な、諭すような声をかけた。\u0005"
    ]
  },
  {
    "op": "55",
    "offset": 8043,
    "args": [
      "u8:8",
      "cgru0510"
    ]
  },
  {
    "op": "15",
    "offset": 8054,
    "args": [
      "\u0001\u0002ルミ「……どうしたの？」\u0005\u0001ルミも神妙な顔で俺の顔を見返す。\u0005"
    ]
  },
  {
    "op": "15",
    "offset": 8117,
    "args": [
      "\u0001\u0002智秋「これを買ってあげたいのは山々だけどね」\u0005"
    ]
  },
  {
    "op": "15",
    "offset": 8166,
    "args": [
      "\u0001\u0002ルミ「…うん」\u0001裕也『………？』\u0005"
    ]
  },
  {
    "op": "15",
    "offset": 8202,
    "args": [
      "\u0001\u0002智秋「これを先に見つけたのは裕也だろ？」\u0005"
    ]
  },
  {
    "op": "15",
    "offset": 8247,
    "args": [
      "\u0001\u0002ルミ「…うん」\u0001裕也『…オイ？』\u0005"
    ]
  },
  {
    "op": "15",
    "offset": 8283,
    "args": [
      "\u0001\u0002智秋「裕也もルミと同じくらいこれが欲しいと思うんだ」\u0005"
    ]
  },
  {
    "op": "15",
    "offset": 8340,
    "args": [
      "\u0001\u0002ルミ「うん」\u0001裕也『チョット待て！』\u0005"
    ]
  },
  {
    "op": "15",
    "offset": 8380,
    "args": [
      "\u0001\u0002智秋「裕也は優しいからああ言ってくれたけど、\u0005\u0001……やっぱりそう言うのはいけないと思わないか？」\u0005"
    ]
  },
  {
    "op": "55",
    "offset": 8479,
    "args": [
      "u8:8",
      "cgru0310"
    ]
  },
  {
    "op": "15",
    "offset": 8490,
    "args": [
      "\u0001\u0002ルミ「…うん……そうだね」\u0001裕也『ダイジョーブ。全然オッケー！ルミちゃんに譲るよ』\u0005"
    ]
  },
  {
    "op": "15",
    "offset": 8576,
    "args": [
      "\u0001\u0002智秋「じゃ…どうすればいいか分かるだろう？」\u0005"
    ]
  },
  {
    "op": "55",
    "offset": 8625,
    "args": [
      "u8:8",
      "cgru0010"
    ]
  },
  {
    "op": "15",
    "offset": 8636,
    "args": [
      "\u0001\u0002ルミ「…わかった。残念だけど裕也ちゃんに譲るね」\u0001裕也『無視してンじゃネーよ！！』\u0005"
    ]
  },
  {
    "op": "15",
    "offset": 8722,
    "args": [
      "\u0001\u0002智秋「…と、言うわけだ。\u0005裕也、責任もってそのシャツ買ってこい」\u0005\u0001よしよし、とルミの頭を撫でながら、裕也にそう宣言した。\u0005"
    ]
  },
  {
    "op": "55",
    "offset": 8846,
    "args": [
      "u8:8",
      "cgyu0210"
    ]
  },
  {
    "op": "15",
    "offset": 8857,
    "args": [
      "\u0001\u0002裕也「勝手にハナシ進めるなっ！\u0005何でオレが…」\u0005\u0001『こんな服買わなきゃならねーんだ』\u0005と裕也は続けたかったんだろうが、ルミの顔を見て言葉を飲み込む。\u0005"
    ]
  },
  {
    "op": "55",
    "offset": 9006,
    "args": [
      "u8:8",
      "cgru0310"
    ]
  },
  {
    "op": "15",
    "offset": 9017,
    "args": [
      "\u0001\u0002ルミ「…裕也ちゃん？」\u0005\u0001ルミが不安そうな顔で裕也を見つめた。\u0005"
    ]
  },
  {
    "op": "55",
    "offset": 9082,
    "args": [
      "u8:8",
      "cgyu0110"
    ]
  },
  {
    "op": "15",
    "offset": 9093,
    "args": [
      "\u0001\u0002裕也「あー…、あははは…」\u0005"
    ]
  },
  {
    "op": "15",
    "offset": 9124,
    "args": [
      "\u0001\u0002智秋「笑って誤魔化すな」\u0005"
    ]
  },
  {
    "op": "55",
    "offset": 9153,
    "args": [
      "u8:8",
      "cgyu0310"
    ]
  },
  {
    "op": "15",
    "offset": 9164,
    "args": [
      "\u0001\u0002裕也「…分かりました。\u0005……買ってきます」\u0005\u0001とぼとぼとカウンターに向かって歩き出す。\u0005"
    ]
  },
  {
    "op": "4C 00",
    "offset": 9252,
    "args": []
  },
  {
    "op": "50 07",
    "offset": 9254,
    "args": []
  },
  {
    "op": "15",
    "offset": 9256,
    "args": [
      "\u0001\u0002ルミ「いってらっしゃーい」\u0005\u0001ルミと二人で裕也君を送り出してやった。\u0005"
    ]
  },
  {
    "op": "15",
    "offset": 9327,
    "args": [
      "\u0001\u0002『…ななせん、…はっぴゃくえん！？\u0005……マジ？』\u0005\u0001遠くの方で何か聞こえた。\u0005"
    ]
  },
  {
    "op": "15",
    "offset": 9405,
    "args": [
      "\u0001\u0002……。\u0005"
    ]
  },
  {
    "op": "15",
    "offset": 9416,
    "args": [
      "\u0001\u0002………。\u0005"
    ]
  },
  {
    "op": "15",
    "offset": 9429,
    "args": [
      "\u0001\u0002そうこうしているうちに裕也が戻ってくる。\u0005\u0001智秋「お帰り～」\u0005\u0001満面の笑みで出迎える俺。\u0005"
    ]
  },
  {
    "op": "55",
    "offset": 9518,
    "args": [
      "u8:8",
      "cgyu0210"
    ]
  },
  {
    "op": "15",
    "offset": 9529,
    "args": [
      "\u0001\u0002裕也「…チアキ」\u0005"
    ]
  },
  {
    "op": "15",
    "offset": 9550,
    "args": [
      "\u0001\u0002智秋「なんだ？」\u0005"
    ]
  },
  {
    "op": "15",
    "offset": 9571,
    "args": [
      "\u0001\u0002裕也「お前、ぜってージゴクに落ちるよ」\u0005"
    ]
  },
  {
    "op": "15",
    "offset": 9614,
    "args": [
      "\u0001\u0002智秋「うん、よく言われる♪」\u0005"
    ]
  },
  {
    "op": "55",
    "offset": 9647,
    "args": [
      "u8:8",
      "cgru0010"
    ]
  },
  {
    "op": "15",
    "offset": 9658,
    "args": [
      "\u0001\u0002ルミ「本当に二人とも仲が良いんだね」\u0005"
    ]
  },
  {
    "op": "4C 00",
    "offset": 9699,
    "args": []
  },
  {
    "op": "50 07",
    "offset": 9701,
    "args": []
  },
  {
    "op": "15",
    "offset": 9703,
    "args": [
      "\u0001\u0002…。\u0005"
    ]
  },
  {
    "op": "15",
    "offset": 9712,
    "args": [
      "\u0001\u0002……。\u0005"
    ]
  },
  {
    "op": "15",
    "offset": 9723,
    "args": [
      "\u0001\u0002………。\u0005"
    ]
  },
  {
    "op": "15",
    "offset": 9736,
    "args": [
      "\u0001\u0002それからしばらくウインドウショッピングを楽しんだ。\u0005もっとも、ルミにとっては途中で買ったクレープの方が嬉しそうだったけど。\u0005"
    ]
  },
  {
    "op": "54",
    "offset": 9862,
    "args": [
      "u8:8",
      "bg03"
    ]
  },
  {
    "op": "15",
    "offset": 9869,
    "args": [
      "\u0001\u0002智秋「さて、そろそろ帰ろうか？」\u0005"
    ]
  },
  {
    "op": "55",
    "offset": 9906,
    "args": [
      "u8:8",
      "cgyu0010"
    ]
  },
  {
    "op": "15",
    "offset": 9917,
    "args": [
      "\u0001\u0002裕也「そうだナ、そろそろ疲れたし…」\u0005"
    ]
  },
  {
    "op": "55",
    "offset": 9958,
    "args": [
      "u8:8",
      "cgru0510"
    ]
  },
  {
    "op": "15",
    "offset": 9969,
    "args": [
      "\u0001\u0002ルミ「うん、そうだね」\u0005\u0001ルミだけは少し残念そうな声だ。\u0005"
    ]
  },
  {
    "op": "4C 00",
    "offset": 10028,
    "args": []
  },
  {
    "op": "50 07",
    "offset": 10030,
    "args": []
  },
  {
    "op": "21",
    "offset": 10032,
    "args": []
  },
  {
    "op": "15",
    "offset": 10033,
    "args": [
      "\u0001\u0002俺が相づちを打とうとした時、\u0005"
    ]
  },
  {
    "op": "5B",
    "offset": 10066,
    "args": [
      "u8:0",
      "se09b.wav"
    ]
  },
  {
    "op": "54",
    "offset": 10078,
    "args": [
      "u8:10",
      "bg03h"
    ]
  },
  {
    "op": "6B",
    "offset": 10086,
    "args": [
      "u8:10"
    ]
  },
  {
    "op": "15",
    "offset": 10088,
    "args": [
      "\u0001\u0002俺は、\u0005奇妙な感覚に囚われた。\u0005"
    ]
  },
  {
    "op": "15",
    "offset": 10122,
    "args": [
      "\u0001\u0002ぞわぞわと皮膚がざわめくような感じ…。\u0005\u0001……視線？\u0005誰かに見られている…！？\u0005"
    ]
  },
  {
    "op": "15",
    "offset": 10202,
    "args": [
      "\u0001\u0002そんな確信が俺を突き動かした。\u0005\u0001辺りを見回し、その視線の持ち主を捜す。\u0005\u0001そして……\u0005ひとつの視線とぶつかった。\u0005"
    ]
  },
  {
    "op": "20",
    "offset": 10316,
    "args": [
      "u8:11"
    ]
  },
  {
    "op": "55",
    "offset": 10318,
    "args": [
      "u8:10",
      "cgsh0400"
    ]
  },
  {
    "op": "15",
    "offset": 10329,
    "args": [
      "\u0001\u0002ゾクッ。\u0005\u0001その瞬間、意味の分からない戦慄が背筋を疾り抜ける。\u0005"
    ]
  },
  {
    "op": "15",
    "offset": 10394,
    "args": [
      "\u0001\u0002「………」\u0005\u0001視線の先にあるものが、じっと俺を見つめた。\u0005\u0001何の感情もなく。\u0005ただ、じっと俺を見つめる。\u0005"
    ]
  },
  {
    "op": "15",
    "offset": 10498,
    "args": [
      "\u0001\u0002それは…\u0005\u0001女の姿を持っていた。\u0005\u0001漆黒の髪を持っていた。\u0005\u0001白磁のような肌を持っていた。\u0005"
    ]
  },
  {
    "op": "15",
    "offset": 10587,
    "args": [
      "\u0001\u0002その瞳は……\u0005血の色に輝いていた。\u0005"
    ]
  },
  {
    "op": "15",
    "offset": 10625,
    "args": [
      "\u0001\u0002不意に、風が吹く。\u0005強い、とても強い風が。\u0005\u0001まるで運命を揺り動かすかのように。\u0005\u0001強く、\u0005強く。\u0005"
    ]
  },
  {
    "op": "15",
    "offset": 10722,
    "args": [
      "\u0001\u0002背筋を冷たい汗がつたう。\u0005俺は無意識のうちに躰を動かそうとした。\u0005…が、躰は動かない。\u0005堅く強張って、ピクリとも動かない。\u0005"
    ]
  },
  {
    "op": "15",
    "offset": 10846,
    "args": [
      "\u0001\u0002「……っ！？」\u0005\u0001……恐怖が俺の躰を思うさま舐め回す。\u0005"
    ]
  },
  {
    "op": "15",
    "offset": 10903,
    "args": [
      "\u0001\u0002咽が渇く。\u0005\u0001唾を飲み込もうと喉を鳴らすと、\u0005自分でも驚くほど大きな音がたった。\u0005しかし渇きは癒されない。\u0005"
    ]
  },
  {
    "op": "15",
    "offset": 11010,
    "args": [
      "\u0001\u0002「………」\u0005"
    ]
  },
  {
    "op": "15",
    "offset": 11025,
    "args": [
      "\u0001\u0002「………」\u0005"
    ]
  },
  {
    "op": "15",
    "offset": 11040,
    "args": [
      "\u0001\u0002「………」\u0005"
    ]
  },
  {
    "op": "15",
    "offset": 11055,
    "args": [
      "\u0001\u0002気が遠くなるくらいの刻が過ぎ、\u0005激しい憔悴の沼に飲まれていく。\u0005\u0001…気が遠くなるくらい\u0005……緩やかに。\u0005"
    ]
  },
  {
    "op": "15",
    "offset": 11158,
    "args": [
      "\u0001\u0002足下から、ゆっくりと……。\u0005"
    ]
  },
  {
    "op": "54",
    "offset": 11189,
    "args": [
      "u8:10",
      "black"
    ]
  },
  {
    "op": "5C",
    "offset": 11197,
    "args": []
  },
  {
    "op": "21",
    "offset": 11198,
    "args": []
  },
  {
    "op": "6B",
    "offset": 11199,
    "args": [
      "u8:10"
    ]
  },
  {
    "op": "15",
    "offset": 11201,
    "args": [
      "\u0001\u0002…"
    ]
  },
  {
    "op": "6B",
    "offset": 11207,
    "args": [
      "u8:10"
    ]
  },
  {
    "op": "15",
    "offset": 11209,
    "args": [
      "\u0001…"
    ]
  },
  {
    "op": "6B",
    "offset": 11214,
    "args": [
      "u8:10"
    ]
  },
  {
    "op": "15",
    "offset": 11216,
    "args": [
      "\u0001…？"
    ]
  },
  {
    "op": "6B",
    "offset": 11223,
    "args": [
      "u8:10"
    ]
  },
  {
    "op": "15",
    "offset": 11225,
    "args": [
      "\u0001\u0002………遠くで声が聞こえる。\u0005"
    ]
  },
  {
    "op": "15",
    "offset": 11256,
    "args": [
      "\u0001\u0002「………」\u0005"
    ]
  },
  {
    "op": "15",
    "offset": 11271,
    "args": [
      "\u0001\u0002「………ちゃ…」\u0005"
    ]
  },
  {
    "op": "15",
    "offset": 11292,
    "args": [
      "\u0001\u0002「…あ…」\u0005\u0001懐かしい声。\u0005"
    ]
  },
  {
    "op": "15",
    "offset": 11321,
    "args": [
      "\u0001\u0002「おにいちゃん！」\u0005"
    ]
  },
  {
    "op": "15",
    "offset": 11344,
    "args": [
      "\u0001\u0002「智秋、大丈夫か？」\u0005"
    ]
  },
  {
    "op": "15",
    "offset": 11369,
    "args": [
      "\u0001\u0002智秋「………？」\u0005\u0001周りの風景が飛び込んできた。\u0005"
    ]
  },
  {
    "op": "54",
    "offset": 11420,
    "args": [
      "u8:10",
      "bg03"
    ]
  },
  {
    "op": "55",
    "offset": 11427,
    "args": [
      "u8:8",
      "cgru0310"
    ]
  },
  {
    "op": "15",
    "offset": 11438,
    "args": [
      "\u0001\u0002智秋「…ルミ？」\u0005"
    ]
  },
  {
    "op": "15",
    "offset": 11459,
    "args": [
      "\u0001\u0002ルミ「おにいちゃん！」\u0005\u0001ルミが泣きそうな顔で俺の様子を伺っている。\u0005"
    ]
  },
  {
    "op": "15",
    "offset": 11530,
    "args": [
      "\u0001\u0002智秋「…どうしたんだ？」\u0005"
    ]
  },
  {
    "op": "55",
    "offset": 11559,
    "args": [
      "u8:8",
      "cgyu0310"
    ]
  },
  {
    "op": "15",
    "offset": 11570,
    "args": [
      "\u0001\u0002裕也「『どうしたんだ？』じゃねーよ！大丈夫なのか？」\u0005"
    ]
  },
  {
    "op": "15",
    "offset": 11627,
    "args": [
      "\u0001\u0002智秋「…何言ってんだ……\u0005"
    ]
  },
  {
    "op": "15",
    "offset": 11656,
    "args": [
      "\u0001途中まで言いかけ、\u0005記憶が甦って\u0001きた。"
    ]
  },
  {
    "op": "6B",
    "offset": 11697,
    "args": [
      "u8:5"
    ]
  },
  {
    "op": "20",
    "offset": 11699,
    "args": [
      "u8:11"
    ]
  },
  {
    "op": "5B",
    "offset": 11701,
    "args": [
      "u8:0",
      "se09b.wav"
    ]
  },
  {
    "op": "15",
    "offset": 11713,
    "args": [
      "\u0001\u0002……同時に恐怖も。\u0005\u0001思い出したように、粘りつく汗が額を流れる。\u0005"
    ]
  },
  {
    "op": "55",
    "offset": 11780,
    "args": [
      "u8:8",
      "cgru0310"
    ]
  },
  {
    "op": "15",
    "offset": 11791,
    "args": [
      "\u0001\u0002ルミ「おにいちゃん、顔が真っ青だよ？」\u0005"
    ]
  },
  {
    "op": "15",
    "offset": 11834,
    "args": [
      "\u0001\u0002智秋「…あ、ああ。大丈夫だ」\u0005"
    ]
  },
  {
    "op": "55",
    "offset": 11867,
    "args": [
      "u8:8",
      "cgyu0310"
    ]
  },
  {
    "op": "15",
    "offset": 11878,
    "args": [
      "\u0001\u0002裕也「どうしたんだよ、いきなり動かなくなったんだぜ？」\u0005"
    ]
  },
  {
    "op": "15",
    "offset": 11937,
    "args": [
      "\u0001\u0002智秋「なあ…\u0005時間、どの位経った？」\u0005"
    ]
  },
  {
    "op": "15",
    "offset": 11977,
    "args": [
      "\u0001\u0002裕也「時間？」\u0005"
    ]
  },
  {
    "op": "15",
    "offset": 11996,
    "args": [
      "\u0001\u0002智秋「…ああ」\u0005"
    ]
  },
  {
    "op": "15",
    "offset": 12015,
    "args": [
      "\u0001\u0002裕也「お前が返事をしなくなってから……、\u0005ざっと二分ってところだ」\u0005"
    ]
  },
  {
    "op": "15",
    "offset": 12085,
    "args": [
      "\u0001\u0002二分！？\u0005……嘘だろ？\u0005"
    ]
  },
  {
    "op": "15",
    "offset": 12111,
    "args": [
      "\u0001\u0002智秋「うぇっ」\u0005\u0001込み上げてくる吐き気に、思わず口を押さえる。\u0005"
    ]
  },
  {
    "op": "4C 00",
    "offset": 12176,
    "args": []
  },
  {
    "op": "50 07",
    "offset": 12178,
    "args": []
  },
  {
    "op": "15",
    "offset": 12180,
    "args": [
      "\u0001\u0002裕也「平気か？」\u0001ルミ「大丈夫？」\u0005\u0001二人が俺を支えた。\u0005"
    ]
  },
  {
    "op": "15",
    "offset": 12238,
    "args": [
      "\u0001\u0002智秋「…大丈夫だ、少し休めば元に戻るよ」\u0005"
    ]
  },
  {
    "op": "15",
    "offset": 12283,
    "args": [
      "\u0001\u0002そう言って辺りを見渡すと、周囲には好奇の目が取り囲んでいた。\u0005仕方なく、心配する二人を制してゆっくりと歩き出す。\u0005"
    ]
  },
  {
    "op": "15",
    "offset": 12399,
    "args": [
      "\u0001\u0002裕也「おい……休んでろよ」\u0005"
    ]
  },
  {
    "op": "15",
    "offset": 12430,
    "args": [
      "\u0001\u0002ルミ「そうだよ、おにいちゃん」\u0005"
    ]
  },
  {
    "op": "15",
    "offset": 12465,
    "args": [
      "\u0001\u0002智秋「……いや……、ここじゃあな……」\u0005\u0001俺の視線の意味に気付いた裕也が、何気ない風を装って俺の隣を歩き出した。\u0005"
    ]
  },
  {
    "op": "15",
    "offset": 12580,
    "args": [
      "\u0001\u0002裕也「……そうだな、家まで戻るか」\u0005"
    ]
  },
  {
    "op": "15",
    "offset": 12619,
    "args": [
      "\u0001\u0002智秋「ルミ……行こう」\u0005"
    ]
  },
  {
    "op": "15",
    "offset": 12646,
    "args": [
      "\u0001\u0002ルミ「う、…うん…」\u0005"
    ]
  },
  {
    "op": "54",
    "offset": 12671,
    "args": [
      "u8:9",
      "black"
    ]
  },
  {
    "op": "21",
    "offset": 12679,
    "args": []
  },
  {
    "op": "15",
    "offset": 12680,
    "args": [
      "\u0001\u0002その後、家に帰った頃には体調は驚くほど回復していた。\u0005何があったんだと訝る二人には、ただの立ちくらみだと言っておいた。\u0005"
    ]
  },
  {
    "op": "15",
    "offset": 12802,
    "args": [
      "\u0001\u0002あまり心配を掛けたくなかったというのもあったし、\u0005実際体調もすっかり元通りになったから。\u0005"
    ]
  },
  {
    "op": "15",
    "offset": 12894,
    "args": [
      "\u0001\u0002でも心の奥底に根を下ろした感情は、\u0005……ずっと晴れないままだったが。\u0005"
    ]
  },
  {
    "op": "18",
    "offset": 12966,
    "args": [
      "snr14M"
    ]
  },
  {
    "op": "FF",
    "offset": 12974,
    "args": []
  }
]