[
  {
    "op": "54",
    "offset": 0,
    "args": [
      "u8:8",
      "black"
    ]
  },
  {
    "op": "20",
    "offset": 8,
    "args": [
      "u8:9"
    ]
  },
  {
    "op": "6B",
    "offset": 10,
    "args": [
      "u8:20"
    ]
  },
  {
    "op": "15",
    "offset": 12,
    "args": [
      "\u0001\u0002俺は講義に出なくなった。\u0005講義に出ても、どうせろくに集中できないから……。\u0005\u0001かと言って何かをしようという気なんて全く起きなかった。\u0005"
    ]
  },
  {
    "op": "15",
    "offset": 146,
    "args": [
      "\u0001\u0002家で時間を潰しても、考え事に思考を埋め尽くされるのは目に見えている。\u0005だから一人で街をぶらついたり、裕也と遊びに行ったりする事で時間を潰した。\u0005"
    ]
  },
  {
    "op": "15",
    "offset": 292,
    "args": [
      "\u0001\u0002朝起きてから夜寝るまで、食事と時間を潰すためだけに費やされる生活。\u0005\u0001それでも、ルミとずっと一緒に過ごすよりは、まだ精神的に楽だった。\u0005"
    ]
  },
  {
    "op": "15",
    "offset": 429,
    "args": [
      "\u0001\u0002ルミとこれからどうするか……。\u0005\u0001俺の頭の中にはその悩みが、こびり付いたように離れなかった。\u0005"
    ]
  },
  {
    "op": "15",
    "offset": 524,
    "args": [
      "\u0001\u0002ルミとは別れたくない。\u0005\u0001でも…もし他人を巻き込んだら……。\u0005\u0001それが気がかりだった。\u0005"
    ]
  },
  {
    "op": "15",
    "offset": 611,
    "args": [
      "\u0001\u0002俺が襲われた時と同じように、周囲の人間が襲われたら……\u0005\u0001……自分のわがままのせいで他人を傷つけてしまう事になる。\u0005それを避けるには……ルミと離れるしかない。\u0005"
    ]
  },
  {
    "op": "15",
    "offset": 771,
    "args": [
      "\u0001\u0002……でもルミはどうなる？\u0005\u0001誰にも頼れないルミは…？\u0005"
    ]
  },
  {
    "op": "15",
    "offset": 826,
    "args": [
      "\u0001\u0002解答のない謎かけ。\u0005出口のない迷路。\u0005\u0001不条理な現実は俺を嘲笑うかのようにその難問を突きつけた。\u0005"
    ]
  },
  {
    "op": "15",
    "offset": 924,
    "args": [
      "\u0001\u0002だとしても……いつか俺は決断しなくてはならない。\u0005\u0001それも遠くない未来に。\u0005"
    ]
  },
  {
    "op": "21",
    "offset": 1001,
    "args": []
  },
  {
    "op": "20",
    "offset": 1002,
    "args": [
      "u8:4"
    ]
  },
  {
    "op": "54",
    "offset": 1004,
    "args": [
      "u8:8",
      "bg05"
    ]
  },
  {
    "op": "55",
    "offset": 1011,
    "args": [
      "u8:8",
      "cgru0300"
    ]
  },
  {
    "op": "15",
    "offset": 1022,
    "args": [
      "\u0001\u0002ルミ「おにいちゃん、今日はどうするの？」\u0005\u0001朝食を食べ終えてぼうっとしていると、ルミが横から声をかけてきた。\u0005"
    ]
  },
  {
    "op": "15",
    "offset": 1133,
    "args": [
      "\u0001\u0002智秋「……え？」\u0005\u0001宙に彷徨わせていた視線を落とし……ルミに向けた。\u0005"
    ]
  },
  {
    "op": "15",
    "offset": 1204,
    "args": [
      "\u0001\u0002ルミ「だって、そろそろ学校に行く時間じゃないの？」\u0005\u0001ルミが怪訝そうな顔をした。\u0005"
    ]
  },
  {
    "op": "15",
    "offset": 1287,
    "args": [
      "\u0001\u0002智秋「あ、…そうだな。そろそろ行かなきゃな」\u0005\u0001俺は曖昧な返事をしてから立ち上がり、食器へ手を伸ばした。\u0005"
    ]
  },
  {
    "op": "55",
    "offset": 1394,
    "args": [
      "u8:8",
      "cgru0000"
    ]
  },
  {
    "op": "15",
    "offset": 1405,
    "args": [
      "\u0001\u0002ルミ「あ、わたしがやるよ。おにいちゃん急ぐんでしょ？」\u0005"
    ]
  },
  {
    "op": "15",
    "offset": 1464,
    "args": [
      "\u0001\u0002智秋「悪いな。じゃあ頼めるかな？」\u0005"
    ]
  },
  {
    "op": "15",
    "offset": 1503,
    "args": [
      "\u0001\u0002ルミ「うん」\u0005\u0001俺は笑顔で頷くルミに背を向けて寝室に向かった。\u0005"
    ]
  },
  {
    "op": "21",
    "offset": 1568,
    "args": []
  },
  {
    "op": "20",
    "offset": 1569,
    "args": [
      "u8:3"
    ]
  },
  {
    "op": "54",
    "offset": 1571,
    "args": [
      "u8:8",
      "black"
    ]
  },
  {
    "op": "54",
    "offset": 1579,
    "args": [
      "u8:8",
      "bg00"
    ]
  },
  {
    "op": "15",
    "offset": 1586,
    "args": [
      "\u0001\u0002「さて……どうしようか…」\u0005\u0001俺は家から少し歩いた所でひとりごちた。\u0005"
    ]
  },
  {
    "op": "15",
    "offset": 1657,
    "args": [
      "\u0001\u0002ルミにはああ言ったものの、ここ何日かは学校に行っていない。今日のようにルミに嘘を付いて、適当にどこかで時間を潰しているのだ。\u0005"
    ]
  },
  {
    "op": "15",
    "offset": 1786,
    "args": [
      "\u0001\u0002……しかし、それはそれで辛い。\u0005\u0001ひとりで時間を潰すという消極的な〝作業〟は、普通に遊ぶよりも遙かに疲れる。\u0005"
    ]
  },
  {
    "op": "15",
    "offset": 1897,
    "args": [
      "\u0001\u0002裕也が暇ならあいつと遊ぶのだが、学校があるからそうもいかないし……。\u0005"
    ]
  },
  {
    "op": "15",
    "offset": 1970,
    "args": [
      "\u0001\u0002「ふう………」\u0005\u0001俺は脚を止め、空を見上げた。\u0005\u0001空は当たり前のように蒼く、のんびりと雲が東に向かって流れていた。\u0005"
    ]
  },
  {
    "op": "15",
    "offset": 2085,
    "args": [
      "\u0001\u0002「学校に行こうか…」\u0005\u0001講義に集中できなくても、身の置き場所が無くて困ることもないし…な。\u0005"
    ]
  },
  {
    "op": "54",
    "offset": 2178,
    "args": [
      "u8:8",
      "black"
    ]
  },
  {
    "op": "15",
    "offset": 2186,
    "args": [
      "\u0001\u0002…。\u0005"
    ]
  },
  {
    "op": "15",
    "offset": 2195,
    "args": [
      "\u0001\u0002……。\u0005"
    ]
  },
  {
    "op": "15",
    "offset": 2206,
    "args": [
      "\u0001\u0002………。\u0005"
    ]
  },
  {
    "op": "54",
    "offset": 2219,
    "args": [
      "u8:8",
      "bg09"
    ]
  },
  {
    "op": "55",
    "offset": 2226,
    "args": [
      "u8:8",
      "cgyu0000"
    ]
  },
  {
    "op": "15",
    "offset": 2237,
    "args": [
      "\u0001\u0002「よ、チアキ。今日は珍しいじゃネーか」\u0005\u0001聞き慣れた声が俺の耳に届いた。\u0005\u0001いつの間にか講義が終わっていたらしい。\u0005"
    ]
  },
  {
    "op": "15",
    "offset": 2352,
    "args": [
      "\u0001\u0002智秋「まあな……」\u0005\u0001俺は窓に向けていた視線を裕也に向けた。\u0005"
    ]
  },
  {
    "op": "15",
    "offset": 2415,
    "args": [
      "\u0001\u0002裕也「…なに寝ぼけた声出してるンだよ」\u0005\u0001呆れた口調でそう言いながら、裕也が口元に苦笑を浮かべた。\u0005"
    ]
  },
  {
    "op": "15",
    "offset": 2516,
    "args": [
      "\u0001\u0002智秋「そうか？」\u0005"
    ]
  },
  {
    "op": "15",
    "offset": 2537,
    "args": [
      "\u0001\u0002裕也「そーだよ。ま、ここで話すのも何だから、いつもんトコ行こうーぜ？」\u0005\u0001そう言ったそばからもう歩き出している。\u0005"
    ]
  },
  {
    "op": "15",
    "offset": 2652,
    "args": [
      "\u0001\u0002引き留めるのも面倒だから、鞄を小脇に抱えて裕也の後を追った。\u0005"
    ]
  },
  {
    "op": "54",
    "offset": 2717,
    "args": [
      "u8:8",
      "black"
    ]
  },
  {
    "op": "54",
    "offset": 2725,
    "args": [
      "u8:8",
      "bg11"
    ]
  },
  {
    "op": "15",
    "offset": 2732,
    "args": [
      "\u0001\u0002裕也「ちょっとそこで待ってろよ。何か飲み物買ってくるからさ。…何がいい？」\u0005"
    ]
  },
  {
    "op": "15",
    "offset": 2811,
    "args": [
      "\u0001\u0002智秋「まかせるよ」\u0005"
    ]
  },
  {
    "op": "15",
    "offset": 2834,
    "args": [
      "\u0001\u0002裕也は小さく肩をすくめて、\u0005\u0001裕也「リョーカイ」\u0005\u0001中庭の通路脇に据え付けられている自販機に向かった。\u0005"
    ]
  },
  {
    "op": "15",
    "offset": 2937,
    "args": [
      "\u0001\u0002俺はベンチに深く寄り掛かりながら、何を見るでもなく、ただ景色を眺めた。\u0005\u0001陽も大分、西の空に傾いていて、しばらくすれば燃えるような夕陽に変わるだろう。\u0005"
    ]
  },
  {
    "op": "55",
    "offset": 3090,
    "args": [
      "u8:8",
      "cgyu0000"
    ]
  },
  {
    "op": "15",
    "offset": 3101,
    "args": [
      "\u0001\u0002「なに、おセンチになってるンだよ。…ほいっ」\u0005\u0001そう言って目の前にクリーム色の細長い缶……カフェオレを差し出された。\u0005"
    ]
  },
  {
    "op": "15",
    "offset": 3220,
    "args": [
      "\u0001\u0002智秋「感傷的にもなるさ……熱っ」\u0005\u0001目の前の缶を掴み、あまりの熱さのために落っことしそうになった。\u0005"
    ]
  },
  {
    "op": "15",
    "offset": 3321,
    "args": [
      "\u0001\u0002裕也「……はあ。ずいぶんとジューショーみたいだな」\u0005\u0001ベンチには座らず、脇のコンクリート製の花壇に腰掛けながら、大袈裟に苦笑してみせる。\u0005"
    ]
  },
  {
    "op": "4C 00",
    "offset": 3460,
    "args": []
  },
  {
    "op": "50 07",
    "offset": 3462,
    "args": []
  },
  {
    "op": "15",
    "offset": 3464,
    "args": [
      "\u0001\u0002智秋「余計なお世話だ」\u0005\u0001自分でも苦笑しながら、今度は気を付けながらカフェオレのプルタブを引いた。甘い匂いが微かに届く。\u0005"
    ]
  },
  {
    "op": "15",
    "offset": 3587,
    "args": [
      "\u0001\u0002智秋「うぇ……甘い」\u0005\u0001一口飲んで眉をひそめた。\u0005"
    ]
  },
  {
    "op": "15",
    "offset": 3638,
    "args": [
      "\u0001\u0002智秋「……そう言えばお前、いっつもこれ飲んでないか？」\u0005"
    ]
  },
  {
    "op": "15",
    "offset": 3697,
    "args": [
      "\u0001\u0002裕也「おいおい……今頃気付いたのか？最近の俺のお気に入りなンだ」\u0005"
    ]
  },
  {
    "op": "15",
    "offset": 3766,
    "args": [
      "\u0001\u0002智秋「マジかよ？よくこんな甘い物飲んでるな」\u0005"
    ]
  },
  {
    "op": "15",
    "offset": 3815,
    "args": [
      "\u0001\u0002裕也「そっか？美味いじゃん」\u0005"
    ]
  },
  {
    "op": "15",
    "offset": 3848,
    "args": [
      "\u0001\u0002智秋「俺はコーヒーにはこだわらない人だけど……こんなの飲んでたら糖尿になりそうだ」\u0005"
    ]
  },
  {
    "op": "15",
    "offset": 3935,
    "args": [
      "\u0001\u0002裕也「ダイジョーブ。ならないと思ったらならないって。『ヤマイは気から』って言うじゃネーか」\u0005"
    ]
  },
  {
    "op": "15",
    "offset": 4030,
    "args": [
      "\u0001\u0002智秋「……言葉の使い方、間違ってると思うぞ」\u0005"
    ]
  },
  {
    "op": "15",
    "offset": 4079,
    "args": [
      "\u0001\u0002裕也「ははは。細かいコト気にしてたら、人間生きていけないって」\u0005\u0001相変わらずのマイペースな調子で、ケタケタと笑った。\u0005"
    ]
  },
  {
    "op": "15",
    "offset": 4198,
    "args": [
      "\u0001\u0002智秋「…はぁ」\u0005\u0001俺は呆れて溜息を吐きながらも、もう一口カフェオレを飲む。甘いけど……喉を通り抜ける熱さが心地よかった。\u0005"
    ]
  },
  {
    "op": "15",
    "offset": 4321,
    "args": [
      "\u0001\u0002裕也も一口飲んで間を置いてから、\u0005\u0001裕也「最近どうしたんだよ、ボケッとしちゃってさ」\u0005\u0001口調はそのままに、そう訊いてきた。\u0005"
    ]
  },
  {
    "op": "15",
    "offset": 4444,
    "args": [
      "\u0001\u0002智秋「……そうか？」\u0005"
    ]
  },
  {
    "op": "15",
    "offset": 4469,
    "args": [
      "\u0001\u0002裕也「そうだよ…」\u0005\u0001裕也は途中で言葉を飲み込み、視線を手にしたカフェオレに落とした。\u0005"
    ]
  },
  {
    "op": "15",
    "offset": 4558,
    "args": [
      "\u0001\u0002智秋「大丈夫。気にしないでくれよ。……多分何とかなるから」\u0005"
    ]
  },
  {
    "op": "15",
    "offset": 4621,
    "args": [
      "\u0001\u0002裕也「……そっか。じゃあオレは用事あるから、そろそろ行くわ」\u0005"
    ]
  },
  {
    "op": "15",
    "offset": 4686,
    "args": [
      "\u0001\u0002智秋「あ、ああ…。またな」\u0005"
    ]
  },
  {
    "op": "15",
    "offset": 4717,
    "args": [
      "\u0001\u0002裕也「またナ。ちゃんと学校来いよ」\u0005\u0001ゆっくりと立ち上がって、ひらひらとその手を振った。\u0005"
    ]
  },
  {
    "op": "15",
    "offset": 4808,
    "args": [
      "\u0001\u0002智秋「気が向いたらな」\u0005"
    ]
  },
  {
    "op": "15",
    "offset": 4835,
    "args": [
      "\u0001\u0002裕也「ははは、タンイ落としても知らねーぜ？」\u0005"
    ]
  },
  {
    "op": "15",
    "offset": 4884,
    "args": [
      "\u0001\u0002智秋「……気を付けるよ」\u0005\u0001冗談っぽく言って応えた。\u0005"
    ]
  },
  {
    "op": "15",
    "offset": 4939,
    "args": [
      "\u0001\u0002裕也が見えなくなってから、俺はカフェオレを脇に置いて、いつものようにベンチに寝転がった。\u0005\u0001天気が良いせいで、横になった途端に軽い睡魔に襲われる。\u0005\u0001心地良いそよ風が、それを応援した。\u0005"
    ]
  },
  {
    "op": "15",
    "offset": 5124,
    "args": [
      "\u0001\u0002「………」\u0005"
    ]
  },
  {
    "op": "15",
    "offset": 5139,
    "args": [
      "\u0001\u0002「何とかなる……か」\u0005\u0001俺は流れていく雲に向かってぽつりと吐き出した。\u0005"
    ]
  },
  {
    "op": "54",
    "offset": 5212,
    "args": [
      "u8:8",
      "black"
    ]
  },
  {
    "op": "15",
    "offset": 5220,
    "args": [
      "\u0001\u0002………。\u0005"
    ]
  },
  {
    "op": "15",
    "offset": 5233,
    "args": [
      "\u0001\u0002……。\u0005"
    ]
  },
  {
    "op": "15",
    "offset": 5244,
    "args": [
      "\u0001\u0002…。\u0005"
    ]
  },
  {
    "op": "15",
    "offset": 5253,
    "args": [
      "\u0001\u0002「…ふぁ…あ」\u0005\u0001間の抜けた欠伸が聞こえたと思ったら、それは俺の物だった。\u0005"
    ]
  },
  {
    "op": "54",
    "offset": 5330,
    "args": [
      "u8:8",
      "bg11n"
    ]
  },
  {
    "op": "15",
    "offset": 5338,
    "args": [
      "\u0001\u0002……あれ？\u0005\u0001目を開けると、辺りは既に薄暗い。\u0005\u0001眠るにしても涼しすぎた。\u0005\u0001軽く身震いをしてから、俺は身を起こした。\u0005"
    ]
  },
  {
    "op": "15",
    "offset": 5455,
    "args": [
      "\u0001\u0002「今……何時だろう？」\u0005\u0001この暗さからしても、とっくに七時はまわっていそうだった。どうやら、ずいぶん眠りこけていたらしい。\u0005\u0001……そろそろ帰らないとな。\u0005"
    ]
  },
  {
    "op": "15",
    "offset": 5608,
    "args": [
      "\u0001\u0002何気なく辺りを見渡すと、裕也に貰ったカフェオレが視界の隅に留まった。俺はもうとっくに冷えてしまった缶を手に取り、一息に残りを飲んだ。\u0005\u0001……やっぱり甘い。\u0005"
    ]
  },
  {
    "op": "15",
    "offset": 5765,
    "args": [
      "\u0001\u0002「ルミ、待ってるだろうな」\u0005\u0001冷えた缶を屑籠に放り投げ、歩き出した。\u0005"
    ]
  },
  {
    "op": "54",
    "offset": 5836,
    "args": [
      "u8:8",
      "black"
    ]
  },
  {
    "op": "21",
    "offset": 5844,
    "args": []
  },
  {
    "op": "6B",
    "offset": 5845,
    "args": [
      "u8:15"
    ]
  },
  {
    "op": "54",
    "offset": 5847,
    "args": [
      "u8:8",
      "bg06n"
    ]
  },
  {
    "op": "15",
    "offset": 5855,
    "args": [
      "\u0001\u0002「………」\u0005"
    ]
  },
  {
    "op": "15",
    "offset": 5870,
    "args": [
      "\u0001\u0002ドアの前。\u0005\u0001五分ほど前から俺はここに立ち竦んでいる。\u0005\u0001決心をつける為に。\u0005"
    ]
  },
  {
    "op": "15",
    "offset": 5947,
    "args": [
      "\u0001\u0002今のまま暮らしていたら、結局あの子を苦しめてしまう事になる。その為に俺はルミに全てを正直に話さなくてはいけない。\u0005\u0001……その為の決心だ。\u0005"
    ]
  },
  {
    "op": "15",
    "offset": 6086,
    "args": [
      "\u0001\u0002「………」\u0005"
    ]
  },
  {
    "op": "15",
    "offset": 6101,
    "args": [
      "\u0001\u0002それから更に五分後、\u0005\u0001俺はようやく決意を固めてドアノブに手をかけた。\u0005"
    ]
  },
  {
    "op": "15",
    "offset": 6174,
    "args": [
      "\u0001\u0002ガチャッ。\u0005"
    ]
  },
  {
    "op": "15",
    "offset": 6189,
    "args": [
      "\u0001\u0002すんなりとドアが開く。\u0005"
    ]
  },
  {
    "op": "15",
    "offset": 6216,
    "args": [
      "\u0001\u0002「ただいま」\u0005"
    ]
  },
  {
    "op": "15",
    "offset": 6233,
    "args": [
      "\u0001\u0002「………」\u0005\u0001しかし返事はない。\u0005"
    ]
  },
  {
    "op": "15",
    "offset": 6268,
    "args": [
      "\u0001\u0002「ルミ？」\u0005\u0001少し大きめの声で呼びかけてみた。\u0005"
    ]
  },
  {
    "op": "15",
    "offset": 6317,
    "args": [
      "\u0001\u0002…。\u0005"
    ]
  },
  {
    "op": "15",
    "offset": 6326,
    "args": [
      "\u0001\u0002……。\u0005"
    ]
  },
  {
    "op": "15",
    "offset": 6337,
    "args": [
      "\u0001\u0002やはり返事はなかった。\u0005\u0001何にしても、ここで突っ立ていても仕方ないか。\u0005\u0001とりあえず部屋に入ろう。\u0005"
    ]
  },
  {
    "op": "54",
    "offset": 6436,
    "args": [
      "u8:8",
      "black"
    ]
  },
  {
    "op": "54",
    "offset": 6444,
    "args": [
      "u8:8",
      "bg21"
    ]
  },
  {
    "op": "15",
    "offset": 6451,
    "args": [
      "\u0001\u0002台所を見渡すと、簡単な食事の用意が整っていた。\u0005\u0001……ルミがやってくれたんだろう。\u0005\u0001どうやら、さっきまでいたみたいだな。\u0005"
    ]
  },
  {
    "op": "54",
    "offset": 6574,
    "args": [
      "u8:8",
      "black"
    ]
  },
  {
    "op": "54",
    "offset": 6582,
    "args": [
      "u8:8",
      "bg04n2"
    ]
  },
  {
    "op": "15",
    "offset": 6591,
    "args": [
      "\u0001\u0002「ルミ？」\u0005\u0001寝室を覗いてみる。\u0005\u0001…だけどルミの姿はない。\u0005"
    ]
  },
  {
    "op": "54",
    "offset": 6652,
    "args": [
      "u8:8",
      "black"
    ]
  },
  {
    "op": "15",
    "offset": 6660,
    "args": [
      "\u0001\u0002…。\u0005"
    ]
  },
  {
    "op": "15",
    "offset": 6669,
    "args": [
      "\u0001\u0002……。\u0005"
    ]
  },
  {
    "op": "15",
    "offset": 6680,
    "args": [
      "\u0001\u0002………。\u0005"
    ]
  },
  {
    "op": "54",
    "offset": 6693,
    "args": [
      "u8:8",
      "bg05n2"
    ]
  },
  {
    "op": "15",
    "offset": 6702,
    "args": [
      "\u0001\u0002家中探したが、結局ルミの姿は見つけられなかった。\u0005\u0001……いったい何処に行ったんだろう。\u0005\u0001俺は途方に暮れた。\u0005"
    ]
  },
  {
    "op": "15",
    "offset": 6811,
    "args": [
      "\u0001\u0002そうだ！書き置きかなにか……。\u0005\u0001ルミが黙って出ていくなんて考えられない。あの子の性格なら……きっと何か残していくだろうから。\u0005"
    ]
  },
  {
    "op": "15",
    "offset": 6940,
    "args": [
      "\u0001\u0002俺は手当たり次第に部屋を探そうと思ったが、以外とすんなり目的の物は見つかった。\u0005\u0001それは、電話の横にあった。\u0005\u0001書いた覚えのないメモ。\u0005"
    ]
  },
  {
    "op": "15",
    "offset": 7075,
    "args": [
      "\u0001\u0002その上に、俺の字ではない文字を見つけた。\u0005\u0001………ルミが書いたんだろうか……、いや、そうとしか考えられない。俺は一番上のページに目を通してみた。\u0005"
    ]
  },
  {
    "op": "15",
    "offset": 7222,
    "args": [
      "\u0001\u0002「〝み…かげ…いけ〟？」\u0005\u0001メモには平仮名で、ただそれだけが書いてあった。\u0005\u0001『みかげいけ』と言えば……思い当たることは一つしかない。\u0005"
    ]
  },
  {
    "op": "15",
    "offset": 7357,
    "args": [
      "\u0001\u0002この辺りの地名……だよな。\u0005\u0001そう言っても、御影池公園くらいしかめぼしい場所は無いけど……。\u0005"
    ]
  },
  {
    "op": "15",
    "offset": 7452,
    "args": [
      "\u0001\u0002嫌な予感が脳裏をかすめた。\u0005\u0001電話の脇にあるメモに書いたって事は……誰かからの電話を受けて、その内容を書き留めたと言う事だろう。\u0005"
    ]
  },
  {
    "op": "15",
    "offset": 7583,
    "args": [
      "\u0001\u0002いったい誰が……。\u0005\u0001俺の家に電話をかけてくる人間なんて数える程しかいない。\u0005"
    ]
  },
  {
    "op": "15",
    "offset": 7662,
    "args": [
      "\u0001\u0002でもルミに用があるやつなんて………。\u0005\u0001悪い予感がどんどん膨らんでくる。\u0005"
    ]
  },
  {
    "op": "15",
    "offset": 7737,
    "args": [
      "\u0001\u0002電気は点けっぱなし、\u0005\u0001鍵は掛けていない……。\u0005\u0001余程慌てて家を出たのか…。\u0005"
    ]
  },
  {
    "op": "15",
    "offset": 7814,
    "args": [
      "\u0001\u0002どうしよう……。\u0005"
    ]
  },
  {
    "op": "17 02 00",
    "offset": 7835,
    "args": [
      "探しに行く",
      "このまま家で待っている",
      ""
    ]
  },
  {
    "op": "11",
    "offset": 7873,
    "args": [
      "u8:22",
      "u16:2",
      "u8:21",
      "u16:1",
      "u16:2",
      "u16:7896"
    ]
  },
  {
    "op": "18",
    "offset": 7884,
    "args": [
      "snr22bM"
    ]
  },
  {
    "op": "10",
    "offset": 7893,
    "args": [
      "u16:7906"
    ]
  },
  {
    "op": "18",
    "offset": 7896,
    "args": [
      "bdendru2"
    ]
  },
  {
    "op": "FF",
    "offset": 7906,
    "args": []
  }
]